odoo/addons/account_export_csv/README.rst
odoo/addons/account_export_csv/__init__.py
odoo/addons/account_export_csv/__manifest__.py
odoo/addons/account_export_csv/i18n/account_export_csv.pot
odoo/addons/account_export_csv/i18n/es_AR.po
odoo/addons/account_export_csv/i18n/fr.po
odoo/addons/account_export_csv/i18n/hr.po
odoo/addons/account_export_csv/i18n/it.po
odoo/addons/account_export_csv/i18n/nl.po
odoo/addons/account_export_csv/i18n/pt.po
odoo/addons/account_export_csv/readme/CONTRBUTORS.rst
odoo/addons/account_export_csv/readme/DESCRIPTION.rst
odoo/addons/account_export_csv/readme/ROADMAP.rst
odoo/addons/account_export_csv/static/description/icon.png
odoo/addons/account_export_csv/static/description/index.html
odoo/addons/account_export_csv/tests/__init__.py
odoo/addons/account_export_csv/tests/test_account_export_csv.py
odoo/addons/account_export_csv/wizard/__init__.py
odoo/addons/account_export_csv/wizard/account_export_csv.py
odoo/addons/account_export_csv/wizard/account_export_csv_view.xml
odoo12_addon_account_export_csv-12.0.1.2.1.dist-info/METADATA
odoo12_addon_account_export_csv-12.0.1.2.1.dist-info/WHEEL
odoo12_addon_account_export_csv-12.0.1.2.1.dist-info/top_level.txt
odoo12_addon_account_export_csv-12.0.1.2.1.dist-info/RECORD
